deptective/__init__.py
deptective/__main__.py
deptective/apt.py
deptective/cache.py
deptective/cli.py
deptective/containers.py
deptective/dependencies.py
deptective/exceptions.py
deptective/logs.py
deptective/package_manager.py
deptective/signals.py
deptective/strace.py
deptective/strace/deptective-files-exist
deptective/strace/deptective-strace
deptective-0.1.0.dist-info/entry_points.txt
deptective-0.1.0.dist-info/licenses/LICENSE
deptective-0.1.0.dist-info/WHEEL
deptective-0.1.0.dist-info/METADATA
deptective-0.1.0.dist-info/RECORD
