Metadata-Version: 2.4
Name: deptective
Version: 0.1.0
Summary: deptective
Author-email: Trail of Bits <opensource@trailofbits.com>
Classifier: Development Status :: 4 - Beta
Classifier: Environment :: Console
Classifier: Intended Audience :: Science/Research
Classifier: License :: OSI Approved :: GNU Lesser General Public License v3 or later (LGPLv3+)
Classifier: Programming Language :: Python :: 3 :: Only
Classifier: Topic :: Utilities
License-File: LICENSE
Requires-Dist: appdirs ~= 1.4.4
Requires-Dist: docker ~= 7.1.0
Requires-Dist: randomname ~= 0.2.1
Requires-Dist: rich ~= 13.4.2
Requires-Dist: typing-extensions ~= 4.12.2;python_version<'3.11'
Requires-Dist: build ; extra == "dev"
Requires-Dist: deptective[lint, test] ; extra == "dev"
Requires-Dist: twine ; extra == "dev"
Requires-Dist: ruff ; extra == "lint"
Requires-Dist: black ; extra == "lint"
Requires-Dist: mypy ; extra == "lint"
Requires-Dist: pytest ; extra == "test"
Requires-Dist: pytest-cov ; extra == "test"
Requires-Dist: coverage[toml] ; extra == "test"
Project-URL: Home, https://github.com/trailofbits/deptective
Provides-Extra: dev
Provides-Extra: lint
Provides-Extra: test
